ezcaptcha/__init__.py
ezcaptcha/error.py
ezcaptcha/language.py
ezcaptcha-1.5.dist-info/LICENSE
ezcaptcha-1.5.dist-info/METADATA
ezcaptcha-1.5.dist-info/WHEEL
ezcaptcha-1.5.dist-info/top_level.txt
ezcaptcha-1.5.dist-info/RECORD
