Metadata-Version: 2.1
Name: ezcaptcha
Version: 1.5
Summary: EzCaptcha python sdk
Home-page: https://github.com/ez-captcha/ezcaptcha-python
Author: EzCaptcha
Author-email: dev@ez-captcha.com
License: MIT
Keywords: EzCaptcha python sdk
Classifier: Development Status :: 4 - Beta
Classifier: Intended Audience :: Developers
Classifier: Natural Language :: English
Classifier: Operating System :: POSIX :: Linux
Classifier: Programming Language :: Python :: 3.9
License-File: LICENSE
